<?xml version="1.0" encoding="utf-8"?>
<HTTPSnapshot xmlns:xsi="http://www.w3.org/2001/XMLSchema-instance" xmlns:xsd="http://www.w3.org/2001/XMLSchema" id="28">
  <HTTPTask id="1440" hostname="www.advantageonlineshopping.com" path="/order/api/v1/carts/559529690" url="https://www.advantageonlineshopping.com/order/api/v1/carts/559529690" ip="54.227.55.203" port="443" connectionId="31" origin="Primary" frame="1" startDateTime="2024-03-12T16:06:43.231+03:00" startTime="69275343" endTime="69275562">
    <HTTPRequest method="DELETE">
      <HTTPHeaders>
        <HTTPHeaderEntity name="Host" index="0">
          <HTTPDataSet>
            <HTTPData dataFilePath="" dfeDataType="Raw" sectionDataType="1">
              <ActualData>d3d3LmFkdmFudGFnZW9ubGluZXNob3BwaW5nLmNvbQ==</ActualData>
            </HTTPData>
          </HTTPDataSet>
          <IsExternalData>false</IsExternalData>
        </HTTPHeaderEntity>
        <HTTPHeaderEntity name="User-Agent" index="1">
          <HTTPDataSet>
            <HTTPData dataFilePath="" dfeDataType="Raw" sectionDataType="1">
              <ActualData>TW96aWxsYS81LjAgKFdpbmRvd3MgTlQgMTAuMDsgV2luNjQ7IHg2NDsgcnY6MTIzLjApIEdlY2tvLzIwMTAwMTAxIEZpcmVmb3gvMTIzLjA=</ActualData>
            </HTTPData>
          </HTTPDataSet>
          <IsExternalData>false</IsExternalData>
        </HTTPHeaderEntity>
        <HTTPHeaderEntity name="Accept" index="2">
          <HTTPDataSet>
            <HTTPData dataFilePath="" dfeDataType="Raw" sectionDataType="1">
              <ActualData>YXBwbGljYXRpb24vanNvbiwgdGV4dC9wbGFpbiwgKi8q</ActualData>
            </HTTPData>
          </HTTPDataSet>
          <IsExternalData>false</IsExternalData>
        </HTTPHeaderEntity>
        <HTTPHeaderEntity name="Accept-Language" index="3">
          <HTTPDataSet>
            <HTTPData dataFilePath="" dfeDataType="Raw" sectionDataType="1">
              <ActualData>cnUtUlUscnU7cT0wLjgsZW4tVVM7cT0wLjUsZW47cT0wLjM=</ActualData>
            </HTTPData>
          </HTTPDataSet>
          <IsExternalData>false</IsExternalData>
        </HTTPHeaderEntity>
        <HTTPHeaderEntity name="Accept-Encoding" index="4">
          <HTTPDataSet>
            <HTTPData dataFilePath="" dfeDataType="Raw" sectionDataType="1">
              <ActualData>Z3ppcCwgZGVmbGF0ZSwgYnI=</ActualData>
            </HTTPData>
          </HTTPDataSet>
          <IsExternalData>false</IsExternalData>
        </HTTPHeaderEntity>
        <HTTPHeaderEntity name="Authorization" index="5">
          <HTTPDataSet>
            <HTTPData dataFilePath="" dfeDataType="Raw" sectionDataType="1">
              <ActualData>QmFzaWMgVjNkWGQxYzZWM2RYTWpBek16RT0=</ActualData>
            </HTTPData>
          </HTTPDataSet>
          <IsExternalData>false</IsExternalData>
        </HTTPHeaderEntity>
        <HTTPHeaderEntity name="Origin" index="6">
          <HTTPDataSet>
            <HTTPData dataFilePath="" dfeDataType="Raw" sectionDataType="1">
              <ActualData>aHR0cHM6Ly93d3cuYWR2YW50YWdlb25saW5lc2hvcHBpbmcuY29t</ActualData>
            </HTTPData>
          </HTTPDataSet>
          <IsExternalData>false</IsExternalData>
        </HTTPHeaderEntity>
        <HTTPHeaderEntity name="DNT" index="7">
          <HTTPDataSet>
            <HTTPData dataFilePath="" dfeDataType="Raw" sectionDataType="1">
              <ActualData>MQ==</ActualData>
            </HTTPData>
          </HTTPDataSet>
          <IsExternalData>false</IsExternalData>
        </HTTPHeaderEntity>
        <HTTPHeaderEntity name="Sec-GPC" index="8">
          <HTTPDataSet>
            <HTTPData dataFilePath="" dfeDataType="Raw" sectionDataType="1">
              <ActualData>MQ==</ActualData>
            </HTTPData>
          </HTTPDataSet>
          <IsExternalData>false</IsExternalData>
        </HTTPHeaderEntity>
        <HTTPHeaderEntity name="Connection" index="9">
          <HTTPDataSet>
            <HTTPData dataFilePath="" dfeDataType="Raw" sectionDataType="1">
              <ActualData>a2VlcC1hbGl2ZQ==</ActualData>
            </HTTPData>
          </HTTPDataSet>
          <IsExternalData>false</IsExternalData>
        </HTTPHeaderEntity>
        <HTTPHeaderEntity name="Referer" index="10">
          <HTTPDataSet>
            <HTTPData dataFilePath="" dfeDataType="Raw" sectionDataType="1">
              <ActualData>aHR0cHM6Ly93d3cuYWR2YW50YWdlb25saW5lc2hvcHBpbmcuY29tLw==</ActualData>
            </HTTPData>
          </HTTPDataSet>
          <IsExternalData>false</IsExternalData>
        </HTTPHeaderEntity>
        <HTTPHeaderEntity name="Cookie" index="11">
          <HTTPDataSet>
            <HTTPData dataFilePath="" dfeDataType="Raw" sectionDataType="1">
              <ActualData>SlNFU1NJT05JRD00NTBBQzM3NTgzNDVGM0M5QkUzRTZGNzAwRDREMEUzMjsgX2dhX1RCUFlFRDhXU1c9R1MxLjEuMTcxMDI0ODY0OC4xLjAuMTcxMDI0ODY0OC4wLjAuMDsgX2dhPUdBMS4xLjg3NDMzMDM3Ny4xNzEwMjQ4NjQ4</ActualData>
            </HTTPData>
          </HTTPDataSet>
          <IsExternalData>false</IsExternalData>
        </HTTPHeaderEntity>
        <HTTPHeaderEntity name="Sec-Fetch-Dest" index="12">
          <HTTPDataSet>
            <HTTPData dataFilePath="" dfeDataType="Raw" sectionDataType="1">
              <ActualData>ZW1wdHk=</ActualData>
            </HTTPData>
          </HTTPDataSet>
          <IsExternalData>false</IsExternalData>
        </HTTPHeaderEntity>
        <HTTPHeaderEntity name="Sec-Fetch-Mode" index="13">
          <HTTPDataSet>
            <HTTPData dataFilePath="" dfeDataType="Raw" sectionDataType="1">
              <ActualData>Y29ycw==</ActualData>
            </HTTPData>
          </HTTPDataSet>
          <IsExternalData>false</IsExternalData>
        </HTTPHeaderEntity>
        <HTTPHeaderEntity name="Sec-Fetch-Site" index="14">
          <HTTPDataSet>
            <HTTPData dataFilePath="" dfeDataType="Raw" sectionDataType="1">
              <ActualData>c2FtZS1vcmlnaW4=</ActualData>
            </HTTPData>
          </HTTPDataSet>
          <IsExternalData>false</IsExternalData>
        </HTTPHeaderEntity>
        <HTTPAllHeaders>
          <HTTPDataSet>
            <HTTPData dataFilePath="" dfeDataType="Raw" sectionDataType="1">
              <ActualData>REVMRVRFIC9vcmRlci9hcGkvdjEvY2FydHMvNTU5NTI5NjkwIEhUVFAvMS4xDQpIb3N0OiB3d3cuYWR2YW50YWdlb25saW5lc2hvcHBpbmcuY29tDQpVc2VyLUFnZW50OiBNb3ppbGxhLzUuMCAoV2luZG93cyBOVCAxMC4wOyBXaW42NDsgeDY0OyBydjoxMjMuMCkgR2Vja28vMjAxMDAxMDEgRmlyZWZveC8xMjMuMA0KQWNjZXB0OiBhcHBsaWNhdGlvbi9qc29uLCB0ZXh0L3BsYWluLCAqLyoNCkFjY2VwdC1MYW5ndWFnZTogcnUtUlUscnU7cT0wLjgsZW4tVVM7cT0wLjUsZW47cT0wLjMNCkFjY2VwdC1FbmNvZGluZzogZ3ppcCwgZGVmbGF0ZSwgYnINCkF1dGhvcml6YXRpb246IEJhc2ljIFYzZFhkMWM2VjNkWE1qQXpNekU9DQpPcmlnaW46IGh0dHBzOi8vd3d3LmFkdmFudGFnZW9ubGluZXNob3BwaW5nLmNvbQ0KRE5UOiAxDQpTZWMtR1BDOiAxDQpDb25uZWN0aW9uOiBrZWVwLWFsaXZlDQpSZWZlcmVyOiBodHRwczovL3d3dy5hZHZhbnRhZ2VvbmxpbmVzaG9wcGluZy5jb20vDQpDb29raWU6IEpTRVNTSU9OSUQ9NDUwQUMzNzU4MzQ1RjNDOUJFM0U2RjcwMEQ0RDBFMzI7IF9nYV9UQlBZRUQ4V1NXPUdTMS4xLjE3MTAyNDg2NDguMS4wLjE3MTAyNDg2NDguMC4wLjA7IF9nYT1HQTEuMS44NzQzMzAzNzcuMTcxMDI0ODY0OA0KU2VjLUZldGNoLURlc3Q6IGVtcHR5DQpTZWMtRmV0Y2gtTW9kZTogY29ycw0KU2VjLUZldGNoLVNpdGU6IHNhbWUtb3JpZ2luDQoNCg==</ActualData>
            </HTTPData>
          </HTTPDataSet>
          <IsExternalData>false</IsExternalData>
        </HTTPAllHeaders>
        <HTTPCookies>
          <HTTPHeaderEntity name="JSESSIONID" index="0">
            <HTTPDataSet>
              <HTTPData dataFilePath="" dfeDataType="Raw" sectionDataType="1">
                <ActualData>NDUwQUMzNzU4MzQ1RjNDOUJFM0U2RjcwMEQ0RDBFMzI=</ActualData>
              </HTTPData>
            </HTTPDataSet>
            <IsExternalData>false</IsExternalData>
          </HTTPHeaderEntity>
          <HTTPHeaderEntity name="_ga_TBPYED8WSW" index="1">
            <HTTPDataSet>
              <HTTPData dataFilePath="" dfeDataType="Raw" sectionDataType="1">
                <ActualData>R1MxLjEuMTcxMDI0ODY0OC4xLjAuMTcxMDI0ODY0OC4wLjAuMA==</ActualData>
              </HTTPData>
            </HTTPDataSet>
            <IsExternalData>false</IsExternalData>
          </HTTPHeaderEntity>
          <HTTPHeaderEntity name="_ga" index="2">
            <HTTPDataSet>
              <HTTPData dataFilePath="" dfeDataType="Raw" sectionDataType="1">
                <ActualData>R0ExLjEuODc0MzMwMzc3LjE3MTAyNDg2NDg=</ActualData>
              </HTTPData>
            </HTTPDataSet>
            <IsExternalData>false</IsExternalData>
          </HTTPHeaderEntity>
        </HTTPCookies>
      </HTTPHeaders>
    </HTTPRequest>
    <HTTPResponse>
      <contentLenght>0</contentLenght>
      <HTTPHeaders>
        <HTTPHeaderEntity name="Server" index="0">
          <HTTPDataSet>
            <HTTPData dataFilePath="" dfeDataType="Raw" sectionDataType="1">
              <ActualData>bmdpbngvMS4xOC4wIChVYnVudHUp</ActualData>
            </HTTPData>
          </HTTPDataSet>
          <IsExternalData>false</IsExternalData>
        </HTTPHeaderEntity>
        <HTTPHeaderEntity name="Date" index="1">
          <HTTPDataSet>
            <HTTPData dataFilePath="" dfeDataType="Raw" sectionDataType="1">
              <ActualData>VHVlLCAxMiBNYXIgMjAyNCAxMzowNTo1NyBHTVQ=</ActualData>
            </HTTPData>
          </HTTPDataSet>
          <IsExternalData>false</IsExternalData>
        </HTTPHeaderEntity>
        <HTTPHeaderEntity name="Content-Type" index="2">
          <HTTPDataSet>
            <HTTPData dataFilePath="" dfeDataType="Raw" sectionDataType="1">
              <ActualData>YXBwbGljYXRpb24vanNvbg==</ActualData>
            </HTTPData>
          </HTTPDataSet>
          <IsExternalData>false</IsExternalData>
        </HTTPHeaderEntity>
        <HTTPHeaderEntity name="Transfer-Encoding" index="3">
          <HTTPDataSet>
            <HTTPData dataFilePath="" dfeDataType="Raw" sectionDataType="1">
              <ActualData>Y2h1bmtlZA==</ActualData>
            </HTTPData>
          </HTTPDataSet>
          <IsExternalData>false</IsExternalData>
        </HTTPHeaderEntity>
        <HTTPHeaderEntity name="Connection" index="4">
          <HTTPDataSet>
            <HTTPData dataFilePath="" dfeDataType="Raw" sectionDataType="1">
              <ActualData>a2VlcC1hbGl2ZQ==</ActualData>
            </HTTPData>
          </HTTPDataSet>
          <IsExternalData>false</IsExternalData>
        </HTTPHeaderEntity>
        <HTTPHeaderEntity name="Access-Control-Allow-Credentials" index="5">
          <HTTPDataSet>
            <HTTPData dataFilePath="" dfeDataType="Raw" sectionDataType="1">
              <ActualData>dHJ1ZQ==</ActualData>
            </HTTPData>
          </HTTPDataSet>
          <IsExternalData>false</IsExternalData>
        </HTTPHeaderEntity>
        <HTTPHeaderEntity name="Access-Control-Allow-Origin" index="6">
          <HTTPDataSet>
            <HTTPData dataFilePath="" dfeDataType="Raw" sectionDataType="1">
              <ActualData>aHR0cHM6Ly93d3cuYWR2YW50YWdlb25saW5lc2hvcHBpbmcuY29t</ActualData>
            </HTTPData>
          </HTTPDataSet>
          <IsExternalData>false</IsExternalData>
        </HTTPHeaderEntity>
        <HTTPHeaderEntity name="Vary" index="7">
          <HTTPDataSet>
            <HTTPData dataFilePath="" dfeDataType="Raw" sectionDataType="1">
              <ActualData>b3JpZ2luLGFjY2VwdC1lbmNvZGluZw==</ActualData>
            </HTTPData>
          </HTTPDataSet>
          <IsExternalData>false</IsExternalData>
        </HTTPHeaderEntity>
        <HTTPHeaderEntity name="Expires" index="8">
          <HTTPDataSet>
            <HTTPData dataFilePath="" dfeDataType="Raw" sectionDataType="1">
              <ActualData>MA==</ActualData>
            </HTTPData>
          </HTTPDataSet>
          <IsExternalData>false</IsExternalData>
        </HTTPHeaderEntity>
        <HTTPHeaderEntity name="Cache-control" index="9">
          <HTTPDataSet>
            <HTTPData dataFilePath="" dfeDataType="Raw" sectionDataType="1">
              <ActualData>bm8tc3RvcmU=</ActualData>
            </HTTPData>
          </HTTPDataSet>
          <IsExternalData>false</IsExternalData>
        </HTTPHeaderEntity>
        <HTTPHeaderEntity name="X-Content-Type-Options" index="10">
          <HTTPDataSet>
            <HTTPData dataFilePath="" dfeDataType="Raw" sectionDataType="1">
              <ActualData>bm9zbmlmZg==</ActualData>
            </HTTPData>
          </HTTPDataSet>
          <IsExternalData>false</IsExternalData>
        </HTTPHeaderEntity>
        <HTTPHeaderEntity name="X-XSS-Protection" index="11">
          <HTTPDataSet>
            <HTTPData dataFilePath="" dfeDataType="Raw" sectionDataType="1">
              <ActualData>MTsgbW9kZT1ibG9jaw==</ActualData>
            </HTTPData>
          </HTTPDataSet>
          <IsExternalData>false</IsExternalData>
        </HTTPHeaderEntity>
        <HTTPHeaderEntity name="X-Frame-Options" index="12">
          <HTTPDataSet>
            <HTTPData dataFilePath="" dfeDataType="Raw" sectionDataType="1">
              <ActualData>REVOWQ==</ActualData>
            </HTTPData>
          </HTTPDataSet>
          <IsExternalData>false</IsExternalData>
        </HTTPHeaderEntity>
        <HTTPHeaderEntity name="Content-Encoding" index="13">
          <HTTPDataSet>
            <HTTPData dataFilePath="" dfeDataType="Raw" sectionDataType="1">
              <ActualData>Z3ppcA==</ActualData>
            </HTTPData>
          </HTTPDataSet>
          <IsExternalData>false</IsExternalData>
        </HTTPHeaderEntity>
        <HTTPHeaderEntity name="Strict-Transport-Security" index="14">
          <HTTPDataSet>
            <HTTPData dataFilePath="" dfeDataType="Raw" sectionDataType="1">
              <ActualData>bWF4LWFnZT0zMTUzNjAwMDsgaW5jbHVkZVN1YkRvbWFpbnM7IHByZWxvYWQ=</ActualData>
            </HTTPData>
          </HTTPDataSet>
          <IsExternalData>false</IsExternalData>
        </HTTPHeaderEntity>
        <HTTPAllHeaders>
          <HTTPDataSet>
            <HTTPData dataFilePath="" dfeDataType="Raw" sectionDataType="1">
              <ActualData>SFRUUC8xLjEgMjAwIA0KU2VydmVyOiBuZ2lueC8xLjE4LjAgKFVidW50dSkNCkRhdGU6IFR1ZSwgMTIgTWFyIDIwMjQgMTM6MDU6NTcgR01UDQpDb250ZW50LVR5cGU6IGFwcGxpY2F0aW9uL2pzb24NClRyYW5zZmVyLUVuY29kaW5nOiBjaHVua2VkDQpDb25uZWN0aW9uOiBrZWVwLWFsaXZlDQpBY2Nlc3MtQ29udHJvbC1BbGxvdy1DcmVkZW50aWFsczogdHJ1ZQ0KQWNjZXNzLUNvbnRyb2wtQWxsb3ctT3JpZ2luOiBodHRwczovL3d3dy5hZHZhbnRhZ2VvbmxpbmVzaG9wcGluZy5jb20NClZhcnk6IG9yaWdpbixhY2NlcHQtZW5jb2RpbmcNCkV4cGlyZXM6IDANCkNhY2hlLWNvbnRyb2w6IG5vLXN0b3JlDQpYLUNvbnRlbnQtVHlwZS1PcHRpb25zOiBub3NuaWZmDQpYLVhTUy1Qcm90ZWN0aW9uOiAxOyBtb2RlPWJsb2NrDQpYLUZyYW1lLU9wdGlvbnM6IERFTlkNCkNvbnRlbnQtRW5jb2Rpbmc6IGd6aXANClN0cmljdC1UcmFuc3BvcnQtU2VjdXJpdHk6IG1heC1hZ2U9MzE1MzYwMDA7IGluY2x1ZGVTdWJEb21haW5zOyBwcmVsb2FkDQoNCg==</ActualData>
            </HTTPData>
          </HTTPDataSet>
          <IsExternalData>false</IsExternalData>
        </HTTPAllHeaders>
      </HTTPHeaders>
      <HTTPBody>
        <HTTPDataSet>
          <HTTPData dataFilePath="" dfeDataType="Raw" sectionDataType="4">
            <ActualData>eyJ1c2VySWQiOjU1OTUyOTY5MCwicHJvZHVjdHNJbkNhcnQiOltdfQ==</ActualData>
          </HTTPData>
        </HTTPDataSet>
        <IsExternalData>false</IsExternalData>
      </HTTPBody>
      <TcpPackets>
        <PacketInfo time="69275562" offset="0" length="614" />
      </TcpPackets>
    </HTTPResponse>
  </HTTPTask>
</HTTPSnapshot>